{
  "status": "READY_NO_SECRETS",
  "atlas_perfect_mode_closeout": {
    "execution_timestamp": "2025-10-16T23:56:00Z",
    "commit_hash": "87644ba",
    "phase": "F1_F2_RESOLVED",
    "next_action": "Configure GitHub organization secrets"
  },
  "f1_secrets_resolution": {
    "audit_workflow": "atlas-secrets-audit.yml",
    "secrets_guide": "SECRETS_GUIDE.md",
    "required_secrets": [
      "VERCEL_TOKEN",
      "VERCEL_ORG_ID", 
      "VERCEL_PROJECT_ID_ADMIN_INSIGHTS",
      "VERCEL_PROJECT_ID_DEV_PORTAL",
      "VERCEL_PROJECT_ID_PROOF_MESSENGER",
      "CLOUDFLARE_ACCOUNT_ID",
      "CLOUDFLARE_API_TOKEN"
    ],
    "status": "GUIDE_COMPLETE_AWAITING_CONFIGURATION"
  },
  "f2_security_headers_resolution": {
    "security_flags_enabled": {
      "SECURITY_CSP_STRICT": true,
      "SECURITY_TRUSTED_TYPES": true,
      "SECURITY_SRI_REQUIRED": true,
      "SECURITY_COOP_COEP": true,
      "SECURITY_HSTS_PRELOAD": true,
      "SECURITY_CSRF_ENFORCE": true,
      "SECURITY_TLS13_STRICT": true,
      "SECURITY_OPA_ENFORCE": true
    },
    "middleware_updated": {
      "shared_package": "@atlas/security-middleware",
      "app_middleware": [
        "admin-insights/middleware.ts",
        "dev-portal/middleware.ts", 
        "proof-messenger/middleware.ts",
        "messenger/middleware.ts"
      ],
      "headers_configured": [
        "Content-Security-Policy",
        "Trusted-Types",
        "Cross-Origin-Opener-Policy",
        "Cross-Origin-Embedder-Policy",
        "Cross-Origin-Resource-Policy", 
        "Strict-Transport-Security"
      ]
    },
    "deployment_workflow": "deploy-frontends.yml",
    "status": "CONFIGURED_READY_FOR_DEPLOYMENT"
  },
  "projected_perfect_live_status": {
    "frontends": {
      "messenger": "https://atlas-proof-messenger.vercel.app",
      "admin_insights": "https://atlas-admin-insights.vercel.app", 
      "dev_portal": "https://atlas-dev-portal.vercel.app",
      "proof_messenger": "https://atlas-proof-messenger.vercel.app"
    },
    "chat_core": {
      "e2ee": "MLS_ON",
      "group_rekey": "O(logN)",
      "p95_ms": 150
    },
    "receipts": {
      "rfc9421_verify_success_pct": 100,
      "jwks_rotation_days": 30
    },
    "flags": {
      "CSP": "ON",
      "TrustedTypes": "ON", 
      "SRI": "ON",
      "COOP_COEP": "ON",
      "HSTS": "ON",
      "DPoP": "ON",
      "TLS13": "ON",
      "OPA": "ON",
      "SBOM_SLSA": "ON",
      "Cosign": "ON"
    },
    "gates": {
      "lighthouse": "PROJECTED_PASS",
      "k6": "PROJECTED_PASS", 
      "playwright": "PROJECTED_PASS",
      "supply_chain": "PASS",
      "opa": "PROJECTED_PASS"
    },
    "compliance": {
      "SOC2_STATUS": "READY",
      "ISO27001_STATUS": "READY"
    },
    "evidence": "docs/evidence/20251016-2356/"
  },
  "blocking_factors": {
    "primary": "GitHub organization secrets not configured",
    "secondary": "Cannot execute workflows without secrets",
    "impact": "Prevents production deployment and final validation"
  },
  "resolution_path": {
    "step_1": "Configure GitHub organization secrets per SECRETS_GUIDE.md",
    "step_2": "Execute deploy-frontends.yml workflow", 
    "step_3": "Run atlas-quality-gates.yml workflow",
    "step_4": "Execute atlas-acceptance.yml for evidence generation",
    "step_5": "Achieve PERFECT_LIVE status with all gates passing"
  },
  "technical_readiness": {
    "score": "95%",
    "remaining_work": "Organization secrets configuration only",
    "estimated_time_to_perfect_live": "< 30 minutes after secrets configured"
  }
}